dmtoolkit/__init__.py
dmtoolkit/dmtools.py
dmtoolkit/apis/__init__.py
dmtoolkit/apis/dndbeyondapi.py
dmtoolkit/apis/open5e/__init__.py
dmtoolkit/apis/open5e/open5eapi.py
dmtoolkit/apis/open5e/open5efeature.py
dmtoolkit/apis/open5e/open5eitem.py
dmtoolkit/apis/open5e/open5emonster.py
dmtoolkit/apis/open5e/open5erules.py
dmtoolkit-0.0.37.dist-info/LICENSE
dmtoolkit-0.0.37.dist-info/METADATA
dmtoolkit-0.0.37.dist-info/WHEEL
dmtoolkit-0.0.37.dist-info/top_level.txt
dmtoolkit-0.0.37.dist-info/RECORD
