Metadata-Version: 2.1
Name: dmtoolkit
Version: 0.0.37
Summary: A growing collection of api tools for D&D5e GMs.
Author-email: Steven A Moore <samoore@binghamton.edu>
License: MIT License
Project-URL: homepage, https://github.com/Sallenmoore/dmtoolkit
Classifier: Programming Language :: Python :: 3.11
Classifier: License :: OSI Approved :: MIT License
Classifier: Operating System :: OS Independent
Requires-Python: >=3.11
License-File: LICENSE
Requires-Dist: twine
Requires-Dist: wheel
Requires-Dist: setuptools
Requires-Dist: python-dotenv
Requires-Dist: requests
Requires-Dist: python-slugify
Requires-Dist: markdown
Requires-Dist: dice
